openapi/batch/__init__.py
openapi/batch/__main__.py
openapi/batch/callbacks.py
openapi/batch/cli.py
openapi/batch/client.py
openapi/batch/export.py
openapi/batch/ids.py
openapi/batch/job.py
openapi/batch/logging_utils.py
openapi/batch/models.py
openapi/batch/retry.py
openapi/batch/store.py
openapi/batch/adapters/__init__.py
openapi/batch/adapters/base.py
openapi/batch/adapters/http_json.py
openapi/batch/adapters/local_echo.py
openapi/batch/providers/__init__.py
openapi/batch/providers/base.py
openapi/batch/providers/gemini_provider.py
openapi/batch/providers/local_echo.py
openapi/batch/providers/openai_provider.py
openapi/batch/providers/registry.py
openapi/batch/runtime/__init__.py
openapi/batch/runtime/emulated.py
openapi_batch-0.1.2.dist-info/licenses/LICENSE
openapi_batch-0.1.2.dist-info/METADATA
openapi_batch-0.1.2.dist-info/WHEEL
openapi_batch-0.1.2.dist-info/entry_points.txt
openapi_batch-0.1.2.dist-info/top_level.txt
openapi_batch-0.1.2.dist-info/RECORD
