Metadata-Version: 2.4
Name: openapi-batch
Version: 0.1.2
Summary: Reliable, async batch execution of LLM requests across providers.
Author: Sireto B.V.
License: MIT License
Keywords: batch,llm,openai,gemini,async,ai,api-client
Classifier: Programming Language :: Python :: 3
Classifier: Programming Language :: Python :: 3 :: Only
Classifier: License :: OSI Approved :: MIT License
Classifier: Operating System :: OS Independent
Classifier: Topic :: Software Development :: Libraries
Requires-Python: >=3.10
License-File: LICENSE
Requires-Dist: httpx>=0.27.0
Requires-Dist: python-dotenv
Provides-Extra: openai
Requires-Dist: openai>=1.0.0; extra == "openai"
Provides-Extra: gemini
Requires-Dist: google-genai>=0.3.0; extra == "gemini"
Provides-Extra: dev
Requires-Dist: pytest>=8.0.0; extra == "dev"
Requires-Dist: ruff>=0.6.0; extra == "dev"
Requires-Dist: build>=1.2.0; extra == "dev"
Requires-Dist: twine>=5.0.0; extra == "dev"
Dynamic: license-file
